{
  "traffic": [
    {
      "title": "Schüsse vor Einfamilienhaus in Berlin-Rudow abgegeben",
      "link": "https://www.rbb24.de/panorama/beitrag/2026/04/schuesse-einfamilienhaus-berlin-rudow-neukoelln.html",
      "date": "Sat, 18 Apr 2026 13:12:13 +0200"
    },
    {
      "title": "Berlin-Wahl: Grüne wollen Jarasch und Graf an Spitze der Landesliste",
      "link": "https://www.rbb24.de/politik/wahl/abgeordnetenhaus/agh-2026/beitraege/berlin-gruene-graf-jarasch-landesliste-spitzenplatz.html",
      "date": "Sat, 18 Apr 2026 13:03:59 +0200"
    },
    {
      "title": "14-Jährige auf E-Scooter von Auto in Berlin erfasst - tot",
      "link": "https://www.rbb24.de/panorama/beitrag/2026/04/berlin-verkehr-unfall-buckow-escooter-maedchen-tot.html",
      "date": "Sat, 18 Apr 2026 12:30:56 +0200"
    },
    {
      "title": "Brandenburgs hohe Öko-Stromproduktion soll für günstigere Energiepreise sorgen",
      "link": "https://www.rbb24.de/wirtschaft/beitrag/2026/04/brandenburg-windraeder-oeko-strom-produktion-preis-vergleich-bayern.html",
      "date": "Sat, 18 Apr 2026 11:27:44 +0200"
    },
    {
      "title": "Post-Filialnetz hat in Brandenburg und Berlin Lücken",
      "link": "https://www.rbb24.de/wirtschaft/beitrag/2026/04/berlin-brandenburg-post-filialluecken-bundesnetzagentur.html",
      "date": "Sat, 18 Apr 2026 10:48:38 +0200"
    },
    {
      "title": "Autokonvoi gegen hohe Spritpreise endet in Berlin",
      "link": "https://www.rbb24.de/panorama/beitrag/2026/04/ostfriesland-berlin-protest-hohe-spritpreise-auto-konvoi-bundestag.html",
      "date": "Sat, 18 Apr 2026 10:22:00 +0200"
    },
    {
      "title": "Wo sich in Berlin und Brandenburg die Zecken verstecken",
      "link": "https://www.rbb24.de/panorama/beitrag/2026/04/zecken-berlin-brandenburg-saison-fsme-borreliose-menschen-tiere.html",
      "date": "Sat, 18 Apr 2026 10:08:21 +0200"
    },
    {
      "title": "Nach Erfolg gegen Köln: Eisbären noch einen Sieg vom Finale entfernt",
      "link": "https://www.rbb24.de/sport/beitrag/2026/04/eishockey-del-halbfinale-spiel-fuenf-eisbaeren-koelner-haie.html",
      "date": "Fri, 17 Apr 2026 22:14:00 +0200"
    },
    {
      "title": "Zeugenaussagen in Berliner Fördergeldaffäre",
      "link": "https://www.rbb24.de/politik/beitrag/2026/04/foerdergeldaffaere-projekte-gegen-antisemitismus-berlin-untersuc.html",
      "date": "Fri, 17 Apr 2026 22:02:00 +0200"
    },
    {
      "title": "Trichinellenfunde bei Wildschweinen in Brandenburg nachgewiesen",
      "link": "https://www.rbb24.de/panorama/beitrag/2026/04/wildschweine-trichinellen-brandenburg.html",
      "date": "Fri, 17 Apr 2026 21:28:22 +0200"
    }
  ],
  "police": [
    {
      "title": "Schussabgaben von Unbekannten",
      "link": "https://www.berlin.de/polizei/polizeimeldungen/2026/pressemitteilung.1662226.php",
      "date": "Sat, 18 Apr 2026 13:20:53 +0200"
    },
    {
      "title": "Tödlicher Verkehrsunfall",
      "link": "https://www.berlin.de/polizei/polizeimeldungen/2026/pressemitteilung.1662225.php",
      "date": "Sat, 18 Apr 2026 12:12:38 +0200"
    },
    {
      "title": "Senior vermisst – Polizei bittet um Mithilfe",
      "link": "https://www.berlin.de/polizei/polizeimeldungen/2026/pressemitteilung.1662158.php",
      "date": "Fri, 17 Apr 2026 15:47:06 +0200"
    },
    {
      "title": "Verkehrsunfall – Fahrradfahrer auf Intensivstation",
      "link": "https://www.berlin.de/polizei/polizeimeldungen/2026/pressemitteilung.1662044.php",
      "date": "Fri, 17 Apr 2026 13:46:56 +0200"
    },
    {
      "title": "Tödliche Auseinandersetzung – Mordkommission und Staatsanwaltschaft ermitteln",
      "link": "https://www.berlin.de/polizei/polizeimeldungen/2026/pressemitteilung.1662035.php",
      "date": "Fri, 17 Apr 2026 13:19:28 +0200"
    },
    {
      "title": "Mutmaßlicher Brandstifter festgenommen",
      "link": "https://www.berlin.de/polizei/polizeimeldungen/2026/pressemitteilung.1662030.php",
      "date": "Fri, 17 Apr 2026 13:03:05 +0200"
    },
    {
      "title": "Nach EC-Karten-Betrug - Festnahme",
      "link": "https://www.berlin.de/polizei/polizeimeldungen/2026/pressemitteilung.1661787.php",
      "date": "Thu, 16 Apr 2026 16:53:25 +0200"
    },
    {
      "title": "Mehrere Brandstiftungen in einer Schule",
      "link": "https://www.berlin.de/polizei/polizeimeldungen/2026/pressemitteilung.1661756.php",
      "date": "Thu, 16 Apr 2026 15:42:50 +0200"
    },
    {
      "title": "Alkoholisiert mit E-Scooter Unfall gebaut – Vater und Tochter verletzt",
      "link": "https://www.berlin.de/polizei/polizeimeldungen/2026/pressemitteilung.1661639.php",
      "date": "Thu, 16 Apr 2026 13:36:24 +0200"
    },
    {
      "title": "Nach Streit im Straßenverkehr – Radfahrer verletzt",
      "link": "https://www.berlin.de/polizei/polizeimeldungen/2026/pressemitteilung.1661627.php",
      "date": "Thu, 16 Apr 2026 13:06:29 +0200"
    }
  ],
  "free_events": [],
  "music_nightlife": [],
  "job_fairs": [],
  "ethics": []
}