{
  "traffic": [
    {
      "title": "Blitzermarathon und Speedweek: Polizei kontrolliert diese Woche",
      "link": "https://www.rbb24.de/panorama/beitrag/2026/04/berlin-brandenburg-speedweek-verkehr-kontrollen-polizei.html",
      "date": "Mon, 13 Apr 2026 08:09:51 +0200"
    },
    {
      "title": "Volker Heise im Interview: \"Tschernobyl war ein Wendepunkt in meinem Leben\"",
      "link": "https://www.rbb24.de/kultur/beitrag/2026/04/tschernobyl-atomunfall-interview-volker-heise.html",
      "date": "Mon, 13 Apr 2026 07:59:44 +0200"
    },
    {
      "title": "Netzentgelte für Großbatterien? Leag zeigt sich \"irritiert\"",
      "link": "https://www.rbb24.de/wirtschaft/beitrag/2026/04/leag-batteriespeicher-netzentgeld-brandenburg.html",
      "date": "Mon, 13 Apr 2026 07:43:32 +0200"
    },
    {
      "title": "Fürstenwalde muss in Stichwahl über neuen Bürgermeister entscheiden",
      "link": "https://www.rbb24.de/politik/beitrag/2026/04/buergermeister-wahl-fuerstenwalde-ergebnis.html",
      "date": "Sun, 12 Apr 2026 20:27:56 +0200"
    },
    {
      "title": "Eishockey: Starke Eisbären siegen verdient, aber knapp gegen Köln",
      "link": "https://www.rbb24.de/sport/beitrag/2026/04/eishockey-del-playoffs-halbfinale-eisbaeren-berlin-koelner-haie.html",
      "date": "Sun, 12 Apr 2026 20:16:31 +0200"
    },
    {
      "title": "Füchse Berlin gewinnen Handball-Krimi in Lemgo",
      "link": "https://www.rbb24.de/sport/beitrag/2026/04/handball-bundesliga-lemgo-fuechse-berlin.html",
      "date": "Sun, 12 Apr 2026 20:14:00 +0200"
    },
    {
      "title": "DBBL-Playoffs: Alba Berlin steht vor Halbfinal-Aus gegen Keltern",
      "link": "https://www.rbb24.de/sport/beitrag/2026/04/damen-basketball-bundesliga-dbbl-playoffs-stars-keltern-alba-berlin.html",
      "date": "Sun, 12 Apr 2026 18:16:21 +0200"
    },
    {
      "title": "Regionalliga: Hertha-Frauen siegen, Union II nur mit Remis",
      "link": "https://www.rbb24.de/sport/beitrag/2026/04/berlin-brandenburg-fussball-frauen-union-hertha-turbine-potsdam.html",
      "date": "Sun, 12 Apr 2026 18:02:00 +0200"
    },
    {
      "title": "3. Liga: Energie Cottbus verliert ärgerlich bei Tabellenführer Osnabrück",
      "link": "https://www.rbb24.de/sport/beitrag/2026/04/fussball-3-liga-tabelle-vfl-osnabrueck-energie-cottbus-engelhardt.html",
      "date": "Sun, 12 Apr 2026 17:33:54 +0200"
    },
    {
      "title": "Zwei Verletzte in ICE: Oberleitung reißt und zerschlägt Fenster",
      "link": "https://www.rbb24.de/panorama/beitrag/2026/04/berlin-ice-zug-oberleitungsschaden.html",
      "date": "Sun, 12 Apr 2026 17:19:46 +0200"
    }
  ],
  "police": [
    {
      "title": "E-Scooter-Fahrer nach Zusammenstoß verletzt",
      "link": "https://www.berlin.de/polizei/polizeimeldungen/2026/pressemitteilung.1660239.php",
      "date": "Sun, 12 Apr 2026 15:54:21 +0200"
    },
    {
      "title": "E-Scooter-Fahrer nach Verkehrsunfall verletzt",
      "link": "https://www.berlin.de/polizei/polizeimeldungen/2026/pressemitteilung.1660237.php",
      "date": "Sun, 12 Apr 2026 15:30:31 +0200"
    },
    {
      "title": "Polizist mit Pfefferspray angegriffen",
      "link": "https://www.berlin.de/polizei/polizeimeldungen/2026/pressemitteilung.1660236.php",
      "date": "Sun, 12 Apr 2026 15:27:16 +0200"
    },
    {
      "title": "Schüsse im Mehrfamilienhaus",
      "link": "https://www.berlin.de/polizei/polizeimeldungen/2026/pressemitteilung.1660235.php",
      "date": "Sun, 12 Apr 2026 15:20:55 +0200"
    },
    {
      "title": "Nach Widerstand – DEIG eingesetzt",
      "link": "https://www.berlin.de/polizei/polizeimeldungen/2026/pressemitteilung.1660234.php",
      "date": "Sun, 12 Apr 2026 15:18:16 +0200"
    },
    {
      "title": "Mann mit Glasflasche angegriffen",
      "link": "https://www.berlin.de/polizei/polizeimeldungen/2026/pressemitteilung.1660233.php",
      "date": "Sun, 12 Apr 2026 14:23:32 +0200"
    },
    {
      "title": "Mann ausgeraubt und Polizei angegriffen",
      "link": "https://www.berlin.de/polizei/polizeimeldungen/2026/pressemitteilung.1660232.php",
      "date": "Sat, 11 Apr 2026 16:52:35 +0200"
    },
    {
      "title": "Diebstahl und Beschädigung einer Staatsflagge",
      "link": "https://www.berlin.de/polizei/polizeimeldungen/2026/pressemitteilung.1660228.php",
      "date": "Sat, 11 Apr 2026 12:56:46 +0200"
    },
    {
      "title": "Schusswaffe abgefeuert",
      "link": "https://www.berlin.de/polizei/polizeimeldungen/2026/pressemitteilung.1660225.php",
      "date": "Sat, 11 Apr 2026 11:36:46 +0200"
    },
    {
      "title": "Allgemeinverfügungen erlassen – Einschränkungen im Bezirk Charlottenburg-Wilmersdorf",
      "link": "https://www.berlin.de/polizei/polizeimeldungen/2026/pressemitteilung.1660122.php",
      "date": "Fri, 10 Apr 2026 13:57:10 +0200"
    }
  ],
  "free_events": [],
  "music_nightlife": [],
  "job_fairs": [],
  "ethics": []
}