{
  "traffic": [
    {
      "title": "2. Fußball-Bundesliga: Hertha BSC empfängt am Samstag Kiel",
      "link": "https://www.rbb24.de/sport/beitrag/2026/04/berlin-fussball-hertha-bsc-holstein-kiel-vorbericht-leitl.html",
      "date": "Thu, 23 Apr 2026 17:25:33 +0200"
    },
    {
      "title": "Berliner Hallenbäder heizen Becken wieder auf 27 Grad",
      "link": "https://www.rbb24.de/panorama/beitrag/2026/04/berliner-baeder-hallen-heizen-auf-27-grad.html",
      "date": "Thu, 23 Apr 2026 17:24:53 +0200"
    },
    {
      "title": "Schah-Sohn Reza Pahlavi besucht Berlin - Tausende demonstrieren",
      "link": "https://www.rbb24.de/politik/beitrag/2026/04/iran-schah-sohn-reza-pahlavi-besucht-berlin.html",
      "date": "Thu, 23 Apr 2026 17:18:38 +0200"
    },
    {
      "title": "Neue Handreichung für Ärzte zu Schwangerschaftsabbrüchen nach Vergewaltigung",
      "link": "https://www.rbb24.de/politik/beitrag/2026/04/handreichung-aerzte-schwangerschaftsabbruch-vergewaltigung-opfer-Berlin.html",
      "date": "Thu, 23 Apr 2026 17:16:48 +0200"
    },
    {
      "title": "Fördergeld-Affäre: Nach diesem Bericht muss Wedl-Wilson gehen",
      "link": "https://www.rbb24.de/politik/beitrag/2026/04/kommentar-berlin-foerdergeld-affaere-wedl-wilson-kultursenatorin.html",
      "date": "Thu, 23 Apr 2026 16:38:01 +0200"
    },
    {
      "title": "Schüsse in Berlin: Spezialabteilung \"Telum\" erhebt erstmals Anklage",
      "link": "https://www.rbb24.de/panorama/beitrag/2026/04/berlin-telum-staatsanwaltschaft-anklage-schuesse-erpressung.html",
      "date": "Thu, 23 Apr 2026 16:01:23 +0200"
    },
    {
      "title": "\"Familiäre Gründe\": Trainerwechsel bei BR Volleys",
      "link": "https://www.rbb24.de/sport/beitrag/2026/04/berlin-volleyball-br-volleys-alexandre-leal-markus-steuerwald-trainer-wechsel.html",
      "date": "Thu, 23 Apr 2026 15:41:49 +0200"
    },
    {
      "title": "Keine Verlängerung: Stalker aus der Prignitz kann elektronische Fußfessel wieder ablegen",
      "link": "https://www.rbb24.de/panorama/beitrag/2026/04/brandenburg-einsatz-fussfessel-stalker-landgericht-neuruppin-ende.html",
      "date": "Thu, 23 Apr 2026 15:39:30 +0200"
    },
    {
      "title": "Fördergeld-Affäre: Chialo und Wedl-Wilson konnten laut Rechnungshof Vorwürfe nicht entkräften",
      "link": "https://www.rbb24.de/politik/beitrag/2026/04/berlin-reaktionen-kultursenatorin-wedl-wilson-foerdergeld-affaere-rechnungshof.html",
      "date": "Thu, 23 Apr 2026 15:35:09 +0200"
    },
    {
      "title": "RE3 soll nicht mehr in Schwedt halten: Kommunalpolitiker protestiern",
      "link": "https://www.rbb24.de/panorama/beitrag/2026/04/schwedt-uckermark-protest-regionalexpress-re3-deutsche-bahn.html",
      "date": "Thu, 23 Apr 2026 15:10:43 +0200"
    }
  ],
  "police": [
    {
      "title": "Drei verletzte Beamte – Polizeihubschrauber im Einsatz",
      "link": "https://www.berlin.de/polizei/polizeimeldungen/2026/pressemitteilung.1664172.php",
      "date": "Thu, 23 Apr 2026 17:00:04 +0200"
    },
    {
      "title": "Mutmaßlicher Wohnungseinbrecher festgenommen",
      "link": "https://www.berlin.de/polizei/polizeimeldungen/2026/pressemitteilung.1664097.php",
      "date": "Thu, 23 Apr 2026 15:32:39 +0200"
    },
    {
      "title": "Autofahrer fährt gegen geparkten Pkw",
      "link": "https://www.berlin.de/polizei/polizeimeldungen/2026/pressemitteilung.1664040.php",
      "date": "Thu, 23 Apr 2026 13:04:00 +0200"
    },
    {
      "title": "Mutter und Kind bei Verkehrsunfall verletzt",
      "link": "https://www.berlin.de/polizei/polizeimeldungen/2026/pressemitteilung.1663971.php",
      "date": "Thu, 23 Apr 2026 12:17:00 +0200"
    },
    {
      "title": "Durchsuchungsbeschlüsse wegen Raubtaten vollstreckt",
      "link": "https://www.berlin.de/polizei/polizeimeldungen/2026/pressemitteilung.1663882.php",
      "date": "Thu, 23 Apr 2026 10:41:51 +0200"
    },
    {
      "title": "Geschwindigkeitskontrollen im Rahmen der ROADPOL-Aktionswoche „Speedweek“ – Polizei Berlin zieht Bilanz",
      "link": "https://www.berlin.de/polizei/polizeimeldungen/2026/pressemitteilung.1663534.php",
      "date": "Wed, 22 Apr 2026 14:44:00 +0200"
    },
    {
      "title": "Junge Frau vermisst – Polizei bittet um Mithilfe",
      "link": "https://www.berlin.de/polizei/polizeimeldungen/2026/pressemitteilung.1663350.php",
      "date": "Wed, 22 Apr 2026 11:13:24 +0200"
    },
    {
      "title": "Frau bei Wohnungsbrand verletzt",
      "link": "https://www.berlin.de/polizei/polizeimeldungen/2026/pressemitteilung.1663011.php",
      "date": "Tue, 21 Apr 2026 14:02:00 +0200"
    },
    {
      "title": "Nach Verkehrsunfall – Fahrradfahrer verstorben",
      "link": "https://www.berlin.de/polizei/polizeimeldungen/2026/pressemitteilung.1662044.php",
      "date": "Tue, 21 Apr 2026 11:45:00 +0200"
    },
    {
      "title": "Auseinandersetzung nach Fußballspiel",
      "link": "https://www.berlin.de/polizei/polizeimeldungen/2026/pressemitteilung.1662588.php",
      "date": "Mon, 20 Apr 2026 13:59:10 +0200"
    }
  ],
  "free_events": [],
  "music_nightlife": [],
  "job_fairs": [],
  "ethics": []
}