{
  "traffic": [
    {
      "title": "Görlitzer Park am 1. Mai auch nachts geöffnet - Grillen verboten",
      "link": "https://www.rbb24.de/panorama/beitrag/2026/04/berlin-1-mai-goerlitzer-park-nachts-offen.html",
      "date": "Fri, 24 Apr 2026 15:56:47 +0200"
    },
    {
      "title": "\"Quartier 206\" in Berlin-Mitte: Versteigerung vorerst gescheitert",
      "link": "https://www.rbb24.de/wirtschaft/beitrag/2026/04/berlin-amtsgericht-versteigerung-luxus-kaufhaus-immobilie-friedrichstrasse-quartier-206.html",
      "date": "Fri, 24 Apr 2026 15:49:02 +0200"
    },
    {
      "title": "40 Jahre Tschernobyl-Katastrophe: Radioaktive Wolke über Berlin",
      "link": "https://www.rbb24.de/panorama/beitrag/2026/04/tschernobyl-atom-reaktor-supergau-berlin-ddr-radioaktiv-akw.html",
      "date": "Fri, 24 Apr 2026 14:54:36 +0200"
    },
    {
      "title": "Hisbollah-Anhänger in Berlin zu fast vier Jahren Haft verurteilt",
      "link": "https://www.rbb24.de/panorama/beitrag/2026/04/berlin-urteil-mann-hisbollah-libanon-terrorismusverdacht-radikalisierung.html",
      "date": "Fri, 24 Apr 2026 14:49:28 +0200"
    },
    {
      "title": "Schüsse in Neuköllner Hermannstraße gefallen - 27-Jähriger verletzt",
      "link": "https://www.rbb24.de/panorama/beitrag/2026/04/berlin-hermannstrasse-polizeieinsatz-mutmasslich-schuss.html",
      "date": "Fri, 24 Apr 2026 14:41:26 +0200"
    },
    {
      "title": "Sedlitzer See im Lausitzer Seenland freigegeben",
      "link": "https://www.rbb24.de/panorama/beitrag/2026/04/brandenburg-lausitz-seenland-sedlitzer-see-freigegeben.html",
      "date": "Fri, 24 Apr 2026 14:34:38 +0200"
    },
    {
      "title": "Flughafen BER: Ryanair kündigt Rückzug vom BER an",
      "link": "https://www.rbb24.de/wirtschaft/beitrag/2026/04/flughafen-ber-ryanair-rueckzug-weniger-fluege-schliessung-basis.html",
      "date": "Fri, 24 Apr 2026 14:21:48 +0200"
    },
    {
      "title": "DHL setzt zweites Solarboot in Berlin ein",
      "link": "https://www.rbb24.de/panorama/beitrag/2026/04/berlin-dhl-zweites-solarboot-pakete-koepenick-osthafen.html",
      "date": "Fri, 24 Apr 2026 14:11:10 +0200"
    },
    {
      "title": "Bund fördert Sanierung von zwölf Brandenburger Sportstätten mit Millionenbetrag",
      "link": "https://www.rbb24.de/sport/beitrag/2026/04/bund-mittel-fuer-sanierung-sportstaetten-brandenburg.html",
      "date": "Fri, 24 Apr 2026 13:55:15 +0200"
    },
    {
      "title": "Tschernobyl-Katastrophe: Ex-Umweltsenator Starnick im Interview",
      "link": "https://www.rbb24.de/panorama/beitrag/2026/04/atom-reaktor-tschernobyl-berlin-radioaktiv-akw-supergau-starnick.html",
      "date": "Fri, 24 Apr 2026 12:50:28 +0200"
    }
  ],
  "police": [
    {
      "title": "Junge Frau wieder da",
      "link": "https://www.berlin.de/polizei/polizeimeldungen/2026/pressemitteilung.1663350.php",
      "date": "Fri, 24 Apr 2026 14:32:00 +0200"
    },
    {
      "title": "Unbekannter schießt auf 27-Jährigen – BAO Ferrum und Ermittlungsgruppe Telum ermitteln",
      "link": "https://www.berlin.de/polizei/polizeimeldungen/2026/pressemitteilung.1664571.php",
      "date": "Fri, 24 Apr 2026 14:01:00 +0200"
    },
    {
      "title": "Geld geraubt und mehrere Personen mit Pfefferspray verletzt",
      "link": "https://www.berlin.de/polizei/polizeimeldungen/2026/pressemitteilung.1664553.php",
      "date": "Fri, 24 Apr 2026 13:30:00 +0200"
    },
    {
      "title": "Festnahmen nach Raubüberfällen auf Spätverkaufsstellen",
      "link": "https://www.berlin.de/polizei/polizeimeldungen/2026/pressemitteilung.1664549.php",
      "date": "Fri, 24 Apr 2026 13:27:00 +0200"
    },
    {
      "title": "Allgemeinverfügung zum 1. Mai 2026 – Einschränkungen im Bereich Treptower Park",
      "link": "https://www.berlin.de/polizei/polizeimeldungen/2026/pressemitteilung.1664400.php",
      "date": "Fri, 24 Apr 2026 11:16:40 +0200"
    },
    {
      "title": "Seniorin nach Verkehrsunfall verletzt",
      "link": "https://www.berlin.de/polizei/polizeimeldungen/2026/pressemitteilung.1664313.php",
      "date": "Fri, 24 Apr 2026 09:49:00 +0200"
    },
    {
      "title": "Drei verletzte Beamte – Polizeihubschrauber im Einsatz",
      "link": "https://www.berlin.de/polizei/polizeimeldungen/2026/pressemitteilung.1664172.php",
      "date": "Thu, 23 Apr 2026 17:00:04 +0200"
    },
    {
      "title": "Mutmaßlicher Wohnungseinbrecher festgenommen",
      "link": "https://www.berlin.de/polizei/polizeimeldungen/2026/pressemitteilung.1664097.php",
      "date": "Thu, 23 Apr 2026 15:32:39 +0200"
    },
    {
      "title": "Autofahrer fährt gegen geparkten Pkw",
      "link": "https://www.berlin.de/polizei/polizeimeldungen/2026/pressemitteilung.1664040.php",
      "date": "Thu, 23 Apr 2026 13:04:00 +0200"
    },
    {
      "title": "Mutter und Kind bei Verkehrsunfall verletzt",
      "link": "https://www.berlin.de/polizei/polizeimeldungen/2026/pressemitteilung.1663971.php",
      "date": "Thu, 23 Apr 2026 12:17:00 +0200"
    }
  ],
  "free_events": [],
  "music_nightlife": [],
  "job_fairs": [],
  "ethics": []
}